datasift_graphite.py
setup.py
datasift_graphite.egg-info/PKG-INFO
datasift_graphite.egg-info/SOURCES.txt
datasift_graphite.egg-info/dependency_links.txt
datasift_graphite.egg-info/entry_points.txt
datasift_graphite.egg-info/pbr.json
datasift_graphite.egg-info/requires.txt
datasift_graphite.egg-info/top_level.txt