Metadata-Version: 1.1
Name: datasift-graphite
Version: 1.2.0
Summary: Graph your Datasift account metrics in Graphite.
Home-page: https://github.com/lextoumbourou/datasift-graphite
Author: Lex Toumbourou
Author-email: lextoumbourou@gmail.com
License: MIT License
Platform: UNKNOWN
Classifier: Programming Language :: Python
Classifier: Programming Language :: Python :: 2
Classifier: Programming Language :: Python :: 2.6
Classifier: Programming Language :: Python :: 2.7
